swarmauri_parser_textblob/TextBlobNounParser.py
swarmauri_parser_textblob/TextBlobSentenceParser.py
swarmauri_parser_textblob/__init__.py
swarmauri_parser_textblob-0.7.5.dist-info/LICENSE
swarmauri_parser_textblob-0.7.5.dist-info/METADATA
swarmauri_parser_textblob-0.7.5.dist-info/WHEEL
swarmauri_parser_textblob-0.7.5.dist-info/entry_points.txt
swarmauri_parser_textblob-0.7.5.dist-info/RECORD
